{
    "guidRelativeVideoInfo": [
        {
            "weMedia": {
                "id": "8326",
                "desc": "这些民生新闻，看完让人感觉自己快要原地爆炸了……",
                "name": "生活大爆炸",
                "headPic": "http://p3.ifengimg.com/ifengimcp/pic/20160729/0d0b3ae1f07bf186ed76_size14_w200_h200.jpg"
            },
            "image": "http://p0.ifengimg.com/a/2016_48/70efaf0b78ee055.jpg",
            "commentNo": "0",
            "playTime": "7787",
            "videoFiles": [
                {
                    "spliteNo": 0,
                    "isSplite": 0,
                    "spliteTime": "",
                    "useType": "mp4350k",
                    "mediaUrl": "http://ips.ifeng.com/video19.ifeng.com/video09/2016/11/22/4369243-280-100-1343.mp4",
                    "filesize": 1959
                },
                {
                    "spliteNo": 0,
                    "isSplite": 0,
                    "spliteTime": "",
                    "useType": "mp4500k",
                    "mediaUrl": "http://ips.ifeng.com/video19.ifeng.com/video09/2016/11/22/4369243-102-008-1343.mp4",
                    "filesize": 3107
                },
                {
                    "spliteNo": 0,
                    "isSplite": 0,
                    "spliteTime": "",
                    "useType": "h265350k",
                    "mediaUrl": "http://ips.ifeng.com/video19.ifeng.com/video09/2016/11/22/4369243-549-140-1343.mp4",
                    "filesize": 1958
                },
                {
                    "spliteNo": 0,
                    "isSplite": 0,
                    "spliteTime": "",
                    "useType": "mp41M",
                    "mediaUrl": "http://ips.ifeng.com/video19.ifeng.com/video09/2016/11/22/4369243-544-079-1343.mp4",
                    "filesize": 5325
                },
                {
                    "spliteNo": 0,
                    "isSplite": 0,
                    "spliteTime": "",
                    "useType": "ts350k",
                    "mediaUrl": "http://ips.ifeng.com/video19.ifeng.com/video09/2016/11/22/4369243-280-100-1343.ts",
                    "filesize": 0
                },
                {
                    "spliteNo": 0,
                    "isSplite": 0,
                    "spliteTime": "",
                    "useType": "ts500k",
                    "mediaUrl": "http://ips.ifeng.com/video19.ifeng.com/video09/2016/11/22/4369243-102-008-1343.ts",
                    "filesize": 0
                },
                {
                    "spliteNo": 0,
                    "isSplite": 0,
                    "spliteTime": "",
                    "useType": "ts1M",
                    "mediaUrl": "http://ips.ifeng.com/video19.ifeng.com/video09/2016/11/22/4369243-544-079-1343.ts",
                    "filesize": 0
                },
                {
                    "spliteNo": 0,
                    "isSplite": 0,
                    "spliteTime": "",
                    "useType": "mp3",
                    "mediaUrl": "http://ips.ifeng.com/video19.ifeng.com/video09/2016/11/22/4369243-543-066-1343.mp3",
                    "filesize": 362
                }
            ],
            "shareTimes": "0",
            "duration": "46",
            "createDate": "2016-11-22 13:43:00",
            "searchPath": "55-56",
            "title": "[相关-1]",
            "name": "香港发生黄金大劫案",
            "cpName": "综合",
            "abstractDesc": "",
            "updateDate": "2016-11-22 13:51:47",
            "guid": "01f74088-e2d4-4fc3-a24b-1ba5b2a44340",
            "mUrl": "http://v.ifeng.com/m/video_4312434.shtml",
            "pcUrl": "http://v.ifeng.com/pc/4312434.shtml",
            "itemId": "4312434"
        },
        {
            "weMedia": {
                "id": "8326",
                "desc": "这些民生新闻，看完让人感觉自己快要原地爆炸了……",
                "name": "生活大爆炸",
                "headPic": "http://p3.ifengimg.com/ifengimcp/pic/20160729/0d0b3ae1f07bf186ed76_size14_w200_h200.jpg"
            },
            "image": "http://p0.ifengimg.com/source2/pmop/storage_img/2016/11/21/06af2429-76a8-4278-829b-e68945dc253d_5.jpg",
            "commentNo": "0",
            "playTime": "173",
            "videoFiles": [
                {
                    "spliteNo": 0,
                    "isSplite": 0,
                    "spliteTime": "",
                    "useType": "mp4350k",
                    "mediaUrl": "http://ips.ifeng.com/video19.ifeng.com/video09/2016/11/21/913727-280-6898767-023501.mp4",
                    "filesize": 5846
                },
                {
                    "spliteNo": 0,
                    "isSplite": 0,
                    "spliteTime": "",
                    "useType": "mp4500k",
                    "mediaUrl": "http://ips.ifeng.com/video19.ifeng.com/video09/2016/11/21/913727-102-998767-023501.mp4",
                    "filesize": 9296
                },
                {
                    "spliteNo": 0,
                    "isSplite": 0,
                    "spliteTime": "",
                    "useType": "mp41M",
                    "mediaUrl": "http://ips.ifeng.com/video19.ifeng.com/video09/2016/11/21/913727-544-8098767-023502.mp4",
                    "filesize": 15917
                },
                {
                    "spliteNo": 0,
                    "isSplite": 0,
                    "spliteTime": "",
                    "useType": "h265350k",
                    "mediaUrl": "http://ips.ifeng.com/video19.ifeng.com/video09/2016/11/21/913727-549-13798767-023503.mp4",
                    "filesize": 5720
                },
                {
                    "spliteNo": 0,
                    "isSplite": 0,
                    "spliteTime": "",
                    "useType": "ts350k",
                    "mediaUrl": "http://ips.ifeng.com/video19.ifeng.com/video09/2016/11/21/913727-280-6898767-023501.ts",
                    "filesize": 0
                },
                {
                    "spliteNo": 0,
                    "isSplite": 0,
                    "spliteTime": "",
                    "useType": "ts500k",
                    "mediaUrl": "http://ips.ifeng.com/video19.ifeng.com/video09/2016/11/21/913727-102-998767-023501.ts",
                    "filesize": 0
                },
                {
                    "spliteNo": 0,
                    "isSplite": 0,
                    "spliteTime": "",
                    "useType": "ts1M",
                    "mediaUrl": "http://ips.ifeng.com/video19.ifeng.com/video09/2016/11/21/913727-544-8098767-023502.ts",
                    "filesize": 0
                },
                {
                    "spliteNo": 0,
                    "isSplite": 0,
                    "spliteTime": "",
                    "useType": "mp3",
                    "mediaUrl": "http://ips.ifeng.com/video19.ifeng.com/video09/2016/11/21/913727-535-066-023502.mp3",
                    "filesize": 1088
                }
            ],
            "shareTimes": "0",
            "duration": "139",
            "createDate": "2016-11-12 12:30:10",
            "searchPath": "55-56",
            "title": "[相关-2]",
            "name": "男子持枪抢劫，被猎枪爆头击杀",
            "cpName": "优酷",
            "abstractDesc": "",
            "updateDate": "2016-11-21 12:13:27",
            "guid": "8330578d-1b4d-4a2a-82f0-6ceed1a67868",
            "mUrl": "http://v.ifeng.com/m/video_4262907.shtml",
            "pcUrl": "http://v.ifeng.com/pc/4262907.shtml",
            "itemId": "4262907"
        },
        {
            "weMedia": {
                "id": "9139",
                "desc": "网罗天下国事家事天下事，穷事囧事搞笑事，事事一网打尽。",
                "name": "网罗天下",
                "headPic": "http://p3.ifengimg.com/ifengimcp/pic/20160918/c1577edef0aa54d2022f_size6_w200_h200.jpg"
            },
            "image": "http://p0.ifengimg.com/pmop/2016/11/12/0693cd1e-3cb0-4a65-972b-b9f2244dbb7e.jpg",
            "commentNo": "5",
            "playTime": "223663",
            "videoFiles": [
                {
                    "spliteNo": 0,
                    "isSplite": 0,
                    "spliteTime": "",
                    "useType": "mp4350k",
                    "mediaUrl": "http://ips.ifeng.com/video19.ifeng.com/video09/2016/11/12/4352474-280-100-2031.mp4",
                    "filesize": 4537
                },
                {
                    "spliteNo": 0,
                    "isSplite": 0,
                    "spliteTime": "",
                    "useType": "mp4500k",
                    "mediaUrl": "http://ips.ifeng.com/video19.ifeng.com/video09/2016/11/12/4352474-102-008-2031.mp4",
                    "filesize": 7226
                },
                {
                    "spliteNo": 0,
                    "isSplite": 0,
                    "spliteTime": "",
                    "useType": "h265350k",
                    "mediaUrl": "http://ips.ifeng.com/video19.ifeng.com/video09/2016/11/12/4352474-549-140-2031.mp4",
                    "filesize": 4712
                },
                {
                    "spliteNo": 0,
                    "isSplite": 0,
                    "spliteTime": "",
                    "useType": "mp41M",
                    "mediaUrl": "http://ips.ifeng.com/video19.ifeng.com/video09/2016/11/12/4352474-544-079-2031.mp4",
                    "filesize": 12396
                },
                {
                    "spliteNo": 0,
                    "isSplite": 0,
                    "spliteTime": "",
                    "useType": "ts350k",
                    "mediaUrl": "http://ips.ifeng.com/video19.ifeng.com/video09/2016/11/12/4352474-280-100-2031.ts",
                    "filesize": 0
                },
                {
                    "spliteNo": 0,
                    "isSplite": 0,
                    "spliteTime": "",
                    "useType": "ts500k",
                    "mediaUrl": "http://ips.ifeng.com/video19.ifeng.com/video09/2016/11/12/4352474-102-008-2031.ts",
                    "filesize": 0
                },
                {
                    "spliteNo": 0,
                    "isSplite": 0,
                    "spliteTime": "",
                    "useType": "ts1M",
                    "mediaUrl": "http://ips.ifeng.com/video19.ifeng.com/video09/2016/11/12/4352474-544-079-2031.ts",
                    "filesize": 0
                },
                {
                    "spliteNo": 0,
                    "isSplite": 0,
                    "spliteTime": "",
                    "useType": "mp3",
                    "mediaUrl": "http://ips.ifeng.com/video19.ifeng.com/video09/2016/11/12/4352474-543-066-2031.mp3",
                    "filesize": 845
                }
            ],
            "shareTimes": "0",
            "duration": "108",
            "createDate": "2016-11-12 20:30:00",
            "searchPath": "55-56",
            "title": "[相关-3]",
            "name": "江苏南通：女子持刀声称抢劫 女员工合力制服",
            "cpName": "京视传媒",
            "abstractDesc": "",
            "updateDate": "2016-11-12 20:33:50",
            "guid": "015d6977-a8d2-11e6-bb86-002590c2aaeb",
            "mUrl": "http://v.ifeng.com/m/video_4264436.shtml",
            "pcUrl": "http://v.ifeng.com/pc/4264436.shtml",
            "itemId": "4264436"
        },
        {
            "weMedia": {
                "id": "9179",
                "desc": "每天都为您提供好玩 奇闻 精彩视频",
                "name": "奇闻精选",
                "headPic": "http://p2.ifengimg.com/ifengimcp/pic/20160919/4f04136e938664300eb0_size19_w201_h200.png"
            },
            "image": "http://p0.ifengimg.com/pmop/2016/11/12/3c6a4574-d6db-4277-9f1b-0c110892d3fc.jpg",
            "commentNo": "0",
            "playTime": "169",
            "videoFiles": [
                {
                    "spliteNo": 0,
                    "isSplite": 0,
                    "spliteTime": "",
                    "useType": "mp4350k",
                    "mediaUrl": "http://ips.ifeng.com/video19.ifeng.com/video09/2016/11/12/867792-280-068-233356.mp4",
                    "filesize": 3863
                },
                {
                    "spliteNo": 0,
                    "isSplite": 0,
                    "spliteTime": "",
                    "useType": "mp4500k",
                    "mediaUrl": "http://ips.ifeng.com/video19.ifeng.com/video09/2016/11/12/867792-102-009-233356.mp4",
                    "filesize": 6156
                },
                {
                    "spliteNo": 0,
                    "isSplite": 0,
                    "spliteTime": "",
                    "useType": "mp41M",
                    "mediaUrl": "http://ips.ifeng.com/video19.ifeng.com/video09/2016/11/12/867792-544-080-233357.mp4",
                    "filesize": 10491
                },
                {
                    "spliteNo": 0,
                    "isSplite": 0,
                    "spliteTime": "",
                    "useType": "h265350k",
                    "mediaUrl": "http://ips.ifeng.com/video19.ifeng.com/video09/2016/11/12/867792-549-137-233358.mp4",
                    "filesize": 3934
                },
                {
                    "spliteNo": 0,
                    "isSplite": 0,
                    "spliteTime": "",
                    "useType": "ts350k",
                    "mediaUrl": "http://ips.ifeng.com/video19.ifeng.com/video09/2016/11/12/867792-280-068-233356.ts",
                    "filesize": 0
                },
                {
                    "spliteNo": 0,
                    "isSplite": 0,
                    "spliteTime": "",
                    "useType": "ts500k",
                    "mediaUrl": "http://ips.ifeng.com/video19.ifeng.com/video09/2016/11/12/867792-102-009-233356.ts",
                    "filesize": 0
                },
                {
                    "spliteNo": 0,
                    "isSplite": 0,
                    "spliteTime": "",
                    "useType": "ts1M",
                    "mediaUrl": "http://ips.ifeng.com/video19.ifeng.com/video09/2016/11/12/867792-544-080-233357.ts",
                    "filesize": 0
                },
                {
                    "spliteNo": 0,
                    "isSplite": 0,
                    "spliteTime": "",
                    "useType": "mp3",
                    "mediaUrl": "http://ips.ifeng.com/video19.ifeng.com/video09/2016/11/12/867792-535-066-233357.mp3",
                    "filesize": 715
                }
            ],
            "shareTimes": "0",
            "duration": "92",
            "createDate": "2016-11-12 23:33:10",
            "searchPath": "51-52",
            "title": "[相关-4]",
            "name": "下班后的警察在超市阻止两个武装抢劫犯",
            "cpName": "今日头条",
            "abstractDesc": "",
            "updateDate": "2016-11-14 14:03:04",
            "guid": "56eba66e-72f8-4f42-b8a1-83cbe254c7ab",
            "mUrl": "http://v.ifeng.com/m/video_4264806.shtml",
            "pcUrl": "http://v.ifeng.com/pc/4264806.shtml",
            "itemId": "4264806"
        },
        {
            "weMedia": {
                "id": "9175",
                "desc": "抓住时时热播视频，呈现视觉冲击",
                "name": "触控前沿视频",
                "headPic": "http://p2.ifengimg.com/ifengimcp/pic/20160919/d4a39ba6513423ea83d8_size37_w203_h200.png"
            },
            "image": "http://p0.ifengimg.com/pmop/2016/11/14/cf6ef4ba-c4d7-4786-b8d1-4de888c9c30d.jpg",
            "commentNo": "0",
            "playTime": "190",
            "videoFiles": [
                {
                    "spliteNo": 0,
                    "isSplite": 0,
                    "spliteTime": "",
                    "useType": "mp4350k",
                    "mediaUrl": "http://ips.ifeng.com/video19.ifeng.com/video09/2016/11/14/868289-280-068-033343.mp4",
                    "filesize": 8255
                },
                {
                    "spliteNo": 0,
                    "isSplite": 0,
                    "spliteTime": "",
                    "useType": "mp4500k",
                    "mediaUrl": "http://ips.ifeng.com/video19.ifeng.com/video09/2016/11/14/868289-102-009-033343.mp4",
                    "filesize": 13188
                },
                {
                    "spliteNo": 0,
                    "isSplite": 0,
                    "spliteTime": "",
                    "useType": "mp41M",
                    "mediaUrl": "http://ips.ifeng.com/video19.ifeng.com/video09/2016/11/14/868289-544-080-033344.mp4",
                    "filesize": 22494
                },
                {
                    "spliteNo": 0,
                    "isSplite": 0,
                    "spliteTime": "",
                    "useType": "h265350k",
                    "mediaUrl": "http://ips.ifeng.com/video19.ifeng.com/video09/2016/11/14/868289-549-137-033345.mp4",
                    "filesize": 8123
                },
                {
                    "spliteNo": 0,
                    "isSplite": 0,
                    "spliteTime": "",
                    "useType": "ts350k",
                    "mediaUrl": "http://ips.ifeng.com/video19.ifeng.com/video09/2016/11/14/868289-280-068-033343.ts",
                    "filesize": 0
                },
                {
                    "spliteNo": 0,
                    "isSplite": 0,
                    "spliteTime": "",
                    "useType": "ts500k",
                    "mediaUrl": "http://ips.ifeng.com/video19.ifeng.com/video09/2016/11/14/868289-102-009-033343.ts",
                    "filesize": 0
                },
                {
                    "spliteNo": 0,
                    "isSplite": 0,
                    "spliteTime": "",
                    "useType": "ts1M",
                    "mediaUrl": "http://ips.ifeng.com/video19.ifeng.com/video09/2016/11/14/868289-544-080-033344.ts",
                    "filesize": 0
                },
                {
                    "spliteNo": 0,
                    "isSplite": 0,
                    "spliteTime": "",
                    "useType": "mp3",
                    "mediaUrl": "http://ips.ifeng.com/video19.ifeng.com/video09/2016/11/14/868289-535-066-033344.mp3",
                    "filesize": 1525
                }
            ],
            "shareTimes": "0",
            "duration": "195",
            "createDate": "2016-11-14 03:33:08",
            "searchPath": "70-73",
            "title": "[相关-5]",
            "name": "亡命徒抢劫泰国金店，大街上拿M4扫射！",
            "cpName": "今日头条",
            "abstractDesc": "",
            "updateDate": "2016-11-18 18:32:26",
            "guid": "98947535-70f1-4d3b-9ce7-ae04cf03560a",
            "mUrl": "http://v.ifeng.com/m/video_4270356.shtml",
            "pcUrl": "http://v.ifeng.com/pc/4270356.shtml",
            "itemId": "4270356"
        },
        {
            "weMedia": {
                "id": "9608",
                "desc": "一手视频官方凤凰号，好看的资讯短视频",
                "name": "一手Video",
                "headPic": "http://p0.ifengimg.com/ifengimcp/pic/20161024/f9db1d5678bc01e4e227_size5_w200_h200.jpg"
            },
            "image": "http://p0.ifengimg.com/source2/pmop/storage_img/2016/11/15/6952a9ba-98dc-464e-a3c7-819467525296_1.jpg",
            "commentNo": "0",
            "playTime": "190",
            "videoFiles": [
                {
                    "spliteNo": 0,
                    "isSplite": 0,
                    "spliteTime": "",
                    "useType": "mp4350k",
                    "mediaUrl": "http://ips.ifeng.com/video19.ifeng.com/video09/2016/11/14/868837-280-6898768-231341.mp4",
                    "filesize": 2347
                },
                {
                    "spliteNo": 0,
                    "isSplite": 0,
                    "spliteTime": "",
                    "useType": "mp4500k",
                    "mediaUrl": "http://ips.ifeng.com/video19.ifeng.com/video09/2016/11/14/868837-102-998768-231341.mp4",
                    "filesize": 3764
                },
                {
                    "spliteNo": 0,
                    "isSplite": 0,
                    "spliteTime": "",
                    "useType": "mp41M",
                    "mediaUrl": "http://ips.ifeng.com/video19.ifeng.com/video09/2016/11/14/868837-544-8098768-231342.mp4",
                    "filesize": 6407
                },
                {
                    "spliteNo": 0,
                    "isSplite": 0,
                    "spliteTime": "",
                    "useType": "h265350k",
                    "mediaUrl": "http://ips.ifeng.com/video19.ifeng.com/video09/2016/11/14/868837-549-13798768-231343.mp4",
                    "filesize": 2141
                },
                {
                    "spliteNo": 0,
                    "isSplite": 0,
                    "spliteTime": "",
                    "useType": "ts350k",
                    "mediaUrl": "http://ips.ifeng.com/video19.ifeng.com/video09/2016/11/14/868837-280-6898768-231341.ts",
                    "filesize": 0
                },
                {
                    "spliteNo": 0,
                    "isSplite": 0,
                    "spliteTime": "",
                    "useType": "ts500k",
                    "mediaUrl": "http://ips.ifeng.com/video19.ifeng.com/video09/2016/11/14/868837-102-998768-231341.ts",
                    "filesize": 0
                },
                {
                    "spliteNo": 0,
                    "isSplite": 0,
                    "spliteTime": "",
                    "useType": "ts1M",
                    "mediaUrl": "http://ips.ifeng.com/video19.ifeng.com/video09/2016/11/14/868837-544-8098768-231342.ts",
                    "filesize": 0
                },
                {
                    "spliteNo": 0,
                    "isSplite": 0,
                    "spliteTime": "",
                    "useType": "mp3",
                    "mediaUrl": "http://ips.ifeng.com/video19.ifeng.com/video09/2016/11/14/868837-535-066-231342.mp3",
                    "filesize": 437
                }
            ],
            "shareTimes": "0",
            "duration": "56",
            "createDate": "2016-11-14 23:12:08",
            "searchPath": "55-56",
            "title": "[相关-6]",
            "name": "不许笑，抢劫呢！男子公交车上亮刀 ",
            "cpName": "秒拍",
            "abstractDesc": "",
            "updateDate": "2016-11-15 13:54:18",
            "guid": "4d778370-d0db-4d63-a659-f780bd7dca5d",
            "mUrl": "http://v.ifeng.com/m/video_4274847.shtml",
            "pcUrl": "http://v.ifeng.com/pc/4274847.shtml",
            "itemId": "4274847"
        },
        {
            "weMedia": {
                "id": "9139",
                "desc": "网罗天下国事家事天下事，穷事囧事搞笑事，事事一网打尽。",
                "name": "网罗天下",
                "headPic": "http://p3.ifengimg.com/ifengimcp/pic/20160918/c1577edef0aa54d2022f_size6_w200_h200.jpg"
            },
            "image": "http://p0.ifengimg.com/pmop/2016/11/16/97a83b46-19c7-4ead-9804-b5aee828b931.jpg",
            "commentNo": "0",
            "playTime": "2435",
            "videoFiles": [
                {
                    "spliteNo": 0,
                    "isSplite": 0,
                    "spliteTime": "",
                    "useType": "mp4350k",
                    "mediaUrl": "http://ips.ifeng.com/video19.ifeng.com/video09/2016/11/16/4359993-280-100-2134.mp4",
                    "filesize": 7635
                },
                {
                    "spliteNo": 0,
                    "isSplite": 0,
                    "spliteTime": "",
                    "useType": "mp4500k",
                    "mediaUrl": "http://ips.ifeng.com/video19.ifeng.com/video09/2016/11/16/4359993-102-008-2134.mp4",
                    "filesize": 12155
                },
                {
                    "spliteNo": 0,
                    "isSplite": 0,
                    "spliteTime": "",
                    "useType": "h265350k",
                    "mediaUrl": "http://ips.ifeng.com/video19.ifeng.com/video09/2016/11/16/4359993-549-140-2134.mp4",
                    "filesize": 7300
                },
                {
                    "spliteNo": 0,
                    "isSplite": 0,
                    "spliteTime": "",
                    "useType": "mp41M",
                    "mediaUrl": "http://ips.ifeng.com/video19.ifeng.com/video09/2016/11/16/4359993-544-079-2134.mp4",
                    "filesize": 20794
                },
                {
                    "spliteNo": 0,
                    "isSplite": 0,
                    "spliteTime": "",
                    "useType": "ts350k",
                    "mediaUrl": "http://ips.ifeng.com/video19.ifeng.com/video09/2016/11/16/4359993-280-100-2134.ts",
                    "filesize": 0
                },
                {
                    "spliteNo": 0,
                    "isSplite": 0,
                    "spliteTime": "",
                    "useType": "ts500k",
                    "mediaUrl": "http://ips.ifeng.com/video19.ifeng.com/video09/2016/11/16/4359993-102-008-2134.ts",
                    "filesize": 0
                },
                {
                    "spliteNo": 0,
                    "isSplite": 0,
                    "spliteTime": "",
                    "useType": "ts1M",
                    "mediaUrl": "http://ips.ifeng.com/video19.ifeng.com/video09/2016/11/16/4359993-544-079-2134.ts",
                    "filesize": 0
                },
                {
                    "spliteNo": 0,
                    "isSplite": 0,
                    "spliteTime": "",
                    "useType": "mp3",
                    "mediaUrl": "http://ips.ifeng.com/video19.ifeng.com/video09/2016/11/16/4359993-543-066-2134.mp3",
                    "filesize": 1422
                }
            ],
            "shareTimes": "0",
            "duration": "181",
            "createDate": "2016-11-16 21:34:00",
            "searchPath": "55-56",
            "title": "[相关-7]",
            "name": "安徽：抢劫收获太少 竟帮受害人开卡透支",
            "cpName": "河北广电",
            "abstractDesc": "",
            "updateDate": "2016-11-16 21:35:42",
            "guid": "01df31d6-ac00-11e6-8723-90b11c1320cd",
            "mUrl": "http://v.ifeng.com/m/video_4284888.shtml",
            "pcUrl": "http://v.ifeng.com/pc/4284888.shtml",
            "itemId": "4284888"
        },
        {
            "weMedia": {
                "id": "9543",
                "desc": "八点你瞅啥！瞅你咋的！",
                "name": "八点你瞅啥",
                "headPic": "http://p0.ifengimg.com/ifengimcp/pic/20160926/77890601a86c4aac05b4_size16_w200_h200.jpg"
            },
            "image": "http://p0.ifengimg.com/pmop/2016/11/18/91acc253-cc27-4336-861c-b1791bb5e66b.jpg",
            "commentNo": "0",
            "playTime": "194",
            "videoFiles": [
                {
                    "spliteNo": 0,
                    "isSplite": 0,
                    "spliteTime": "",
                    "useType": "mp4350k",
                    "mediaUrl": "http://ips.ifeng.com/video19.ifeng.com/video09/2016/11/18/892593-280-068-163406.mp4",
                    "filesize": 5792
                },
                {
                    "spliteNo": 0,
                    "isSplite": 0,
                    "spliteTime": "",
                    "useType": "mp4500k",
                    "mediaUrl": "http://ips.ifeng.com/video19.ifeng.com/video09/2016/11/18/892593-102-009-163405.mp4",
                    "filesize": 9251
                },
                {
                    "spliteNo": 0,
                    "isSplite": 0,
                    "spliteTime": "",
                    "useType": "mp41M",
                    "mediaUrl": "http://ips.ifeng.com/video19.ifeng.com/video09/2016/11/18/892593-544-080-163407.mp4",
                    "filesize": 15832
                },
                {
                    "spliteNo": 0,
                    "isSplite": 0,
                    "spliteTime": "",
                    "useType": "h265350k",
                    "mediaUrl": "http://ips.ifeng.com/video19.ifeng.com/video09/2016/11/18/892593-549-137-163407.mp4",
                    "filesize": 5859
                },
                {
                    "spliteNo": 0,
                    "isSplite": 0,
                    "spliteTime": "",
                    "useType": "ts350k",
                    "mediaUrl": "http://ips.ifeng.com/video19.ifeng.com/video09/2016/11/18/892593-280-068-163406.ts",
                    "filesize": 0
                },
                {
                    "spliteNo": 0,
                    "isSplite": 0,
                    "spliteTime": "",
                    "useType": "ts500k",
                    "mediaUrl": "http://ips.ifeng.com/video19.ifeng.com/video09/2016/11/18/892593-102-009-163405.ts",
                    "filesize": 0
                },
                {
                    "spliteNo": 0,
                    "isSplite": 0,
                    "spliteTime": "",
                    "useType": "ts1M",
                    "mediaUrl": "http://ips.ifeng.com/video19.ifeng.com/video09/2016/11/18/892593-544-080-163407.ts",
                    "filesize": 0
                },
                {
                    "spliteNo": 0,
                    "isSplite": 0,
                    "spliteTime": "",
                    "useType": "mp3",
                    "mediaUrl": "http://ips.ifeng.com/video19.ifeng.com/video09/2016/11/18/892593-535-066-163406.mp3",
                    "filesize": 1080
                }
            ],
            "shareTimes": "0",
            "duration": "138",
            "createDate": "2016-11-18 16:33:04",
            "searchPath": "105-107",
            "title": "[相关-8]",
            "name": "美女白日遭遇抢劫，机智劫匪抢手机后脱身",
            "cpName": "今日头条",
            "abstractDesc": "",
            "updateDate": "2016-11-21 15:17:40",
            "guid": "46b838b0-c72c-43f6-afb4-245795738c58",
            "mUrl": "http://v.ifeng.com/m/video_4295430.shtml",
            "pcUrl": "http://v.ifeng.com/pc/4295430.shtml",
            "itemId": "4295430"
        },
        {
            "weMedia": {
                "id": "8342",
                "desc": "交通事故现场监控合集，公路上那些事儿",
                "name": "不转不是老司机",
                "headPic": "http://p0.ifengimg.com/ifengimcp/pic/20160729/9b66c3abea407fd6a985_size13_w200_h200.jpg"
            },
            "image": "http://p0.ifengimg.com/pmop/2016/11/20/1c335023-e3b9-4223-9bcd-57b51822dbf6.jpg",
            "commentNo": "0",
            "playTime": "176",
            "videoFiles": [
                {
                    "spliteNo": 0,
                    "isSplite": 0,
                    "spliteTime": "",
                    "useType": "mp4350k",
                    "mediaUrl": "http://ips.ifeng.com/video19.ifeng.com/video09/2016/11/20/907648-280-068-095854.mp4",
                    "filesize": 8893
                },
                {
                    "spliteNo": 0,
                    "isSplite": 0,
                    "spliteTime": "",
                    "useType": "mp4500k",
                    "mediaUrl": "http://ips.ifeng.com/video19.ifeng.com/video09/2016/11/20/907648-102-009-095853.mp4",
                    "filesize": 14161
                },
                {
                    "spliteNo": 0,
                    "isSplite": 0,
                    "spliteTime": "",
                    "useType": "mp41M",
                    "mediaUrl": "http://ips.ifeng.com/video19.ifeng.com/video09/2016/11/20/907648-544-080-095854.mp4",
                    "filesize": 24286
                },
                {
                    "spliteNo": 0,
                    "isSplite": 0,
                    "spliteTime": "",
                    "useType": "h265350k",
                    "mediaUrl": "http://ips.ifeng.com/video19.ifeng.com/video09/2016/11/20/907648-549-137-095855.mp4",
                    "filesize": 9154
                },
                {
                    "spliteNo": 0,
                    "isSplite": 0,
                    "spliteTime": "",
                    "useType": "ts350k",
                    "mediaUrl": "http://ips.ifeng.com/video19.ifeng.com/video09/2016/11/20/907648-280-068-095854.ts",
                    "filesize": 0
                },
                {
                    "spliteNo": 0,
                    "isSplite": 0,
                    "spliteTime": "",
                    "useType": "ts500k",
                    "mediaUrl": "http://ips.ifeng.com/video19.ifeng.com/video09/2016/11/20/907648-102-009-095853.ts",
                    "filesize": 0
                },
                {
                    "spliteNo": 0,
                    "isSplite": 0,
                    "spliteTime": "",
                    "useType": "ts1M",
                    "mediaUrl": "http://ips.ifeng.com/video19.ifeng.com/video09/2016/11/20/907648-544-080-095854.ts",
                    "filesize": 0
                },
                {
                    "spliteNo": 0,
                    "isSplite": 0,
                    "spliteTime": "",
                    "useType": "mp3",
                    "mediaUrl": "http://ips.ifeng.com/video19.ifeng.com/video09/2016/11/20/907648-535-066-095854.mp3",
                    "filesize": 1655
                }
            ],
            "shareTimes": "0",
            "duration": "212",
            "createDate": "2016-11-20 09:54:09",
            "searchPath": "55-56",
            "title": "[相关-9]",
            "name": "悲剧：即将结婚22岁女生 被窃贼捆绑抢劫后奸杀",
            "cpName": "今日头条",
            "abstractDesc": "",
            "updateDate": "2016-11-21 15:27:12",
            "guid": "8b8078cf-3507-4869-84ef-7055df05b700",
            "mUrl": "http://v.ifeng.com/m/video_4304512.shtml",
            "pcUrl": "http://v.ifeng.com/pc/4304512.shtml",
            "itemId": "4304512"
        },
        {
            "weMedia": {
                "id": "9139",
                "desc": "网罗天下国事家事天下事，穷事囧事搞笑事，事事一网打尽。",
                "name": "网罗天下",
                "headPic": "http://p3.ifengimg.com/ifengimcp/pic/20160918/c1577edef0aa54d2022f_size6_w200_h200.jpg"
            },
            "image": "http://p0.ifengimg.com/pmop/2016/05/21/6964fc20-258a-43f0-9089-761d62556bf2.jpg",
            "commentNo": "4",
            "playTime": "10435",
            "videoFiles": [
                {
                    "spliteNo": 0,
                    "isSplite": 0,
                    "spliteTime": "",
                    "useType": "mp4350k",
                    "mediaUrl": "http://ips.ifeng.com/video19.ifeng.com/video09/2016/05/21/4036115-280-100-0739.mp4",
                    "filesize": 19776
                },
                {
                    "spliteNo": 0,
                    "isSplite": 0,
                    "spliteTime": "",
                    "useType": "mp4500k",
                    "mediaUrl": "http://ips.ifeng.com/video19.ifeng.com/video09/2016/05/21/4036115-102-008-0739.mp4",
                    "filesize": 31523
                },
                {
                    "spliteNo": 0,
                    "isSplite": 0,
                    "spliteTime": "",
                    "useType": "mp41M",
                    "mediaUrl": "http://ips.ifeng.com/video19.ifeng.com/video09/2016/05/21/4036115-544-079-0739.mp4",
                    "filesize": 53938
                },
                {
                    "spliteNo": 0,
                    "isSplite": 0,
                    "spliteTime": "",
                    "useType": "ts350k",
                    "mediaUrl": "http://ips.ifeng.com/video19.ifeng.com/video09/2016/05/21/4036115-280-100-0739.ts",
                    "filesize": 0
                },
                {
                    "spliteNo": 0,
                    "isSplite": 0,
                    "spliteTime": "",
                    "useType": "ts500k",
                    "mediaUrl": "http://ips.ifeng.com/video19.ifeng.com/video09/2016/05/21/4036115-102-008-0739.ts",
                    "filesize": 0
                },
                {
                    "spliteNo": 0,
                    "isSplite": 0,
                    "spliteTime": "",
                    "useType": "ts1M",
                    "mediaUrl": "http://ips.ifeng.com/video19.ifeng.com/video09/2016/05/21/4036115-544-079-0739.ts",
                    "filesize": 0
                },
                {
                    "spliteNo": 0,
                    "isSplite": 0,
                    "spliteTime": "",
                    "useType": "mp3",
                    "mediaUrl": "http://ips.ifeng.com/video19.ifeng.com/video09/2016/05/21/4036115-543-066-0739.mp3",
                    "filesize": 3671
                }
            ],
            "shareTimes": "0",
            "duration": "470",
            "createDate": "2016-05-21 07:38:00",
            "searchPath": "57-58",
            "title": "[相关-10]",
            "name": "《“黄金”大劫案》 ",
            "cpName": "山东卫视",
            "abstractDesc": "",
            "updateDate": "2016-05-21 07:38:00",
            "guid": "011b8e71-afab-419a-8723-cb81875207f3",
            "mUrl": "http://v.ifeng.com/m/video_530674.shtml",
            "pcUrl": "http://v.ifeng.com/pc/530674.shtml",
            "itemId": "530674"
        },
        {
            "weMedia": {
                "id": "9139",
                "desc": "网罗天下国事家事天下事，穷事囧事搞笑事，事事一网打尽。",
                "name": "网罗天下",
                "headPic": "http://p3.ifengimg.com/ifengimcp/pic/20160918/c1577edef0aa54d2022f_size6_w200_h200.jpg"
            },
            "image": "http://y0.ifengimg.com/pmop/2015/09/11/1f1814b7-397c-4746-9e01-eafe75930634.jpg",
            "commentNo": "0",
            "playTime": "9405",
            "videoFiles": [
                {
                    "spliteNo": 0,
                    "isSplite": 0,
                    "spliteTime": "",
                    "useType": "mp4350k",
                    "mediaUrl": "http://ips.ifeng.com/video19.ifeng.com/video09/2015/09/11/3539763-280-100-0024.mp4",
                    "filesize": 13267
                },
                {
                    "spliteNo": 0,
                    "isSplite": 0,
                    "spliteTime": "",
                    "useType": "mp4500k",
                    "mediaUrl": "http://ips.ifeng.com/video19.ifeng.com/video09/2015/09/11/3539763-102-008-0023.mp4",
                    "filesize": 21183
                },
                {
                    "spliteNo": 0,
                    "isSplite": 0,
                    "spliteTime": "",
                    "useType": "mp41M",
                    "mediaUrl": "http://ips.ifeng.com/video19.ifeng.com/video09/2015/09/11/3539763-544-079-0024.mp4",
                    "filesize": 36215
                },
                {
                    "spliteNo": 0,
                    "isSplite": 0,
                    "spliteTime": "",
                    "useType": "ts350k",
                    "mediaUrl": "http://ips.ifeng.com/video19.ifeng.com/video09/2015/09/11/3539763-280-100-0024.ts",
                    "filesize": 0
                },
                {
                    "spliteNo": 0,
                    "isSplite": 0,
                    "spliteTime": "",
                    "useType": "ts500k",
                    "mediaUrl": "http://ips.ifeng.com/video19.ifeng.com/video09/2015/09/11/3539763-102-008-0023.ts",
                    "filesize": 0
                },
                {
                    "spliteNo": 0,
                    "isSplite": 0,
                    "spliteTime": "",
                    "useType": "ts1M",
                    "mediaUrl": "http://ips.ifeng.com/video19.ifeng.com/video09/2015/09/11/3539763-544-079-0024.ts",
                    "filesize": 0
                },
                {
                    "spliteNo": 0,
                    "isSplite": 0,
                    "spliteTime": "",
                    "useType": "mp3",
                    "mediaUrl": "http://ips.ifeng.com/video19.ifeng.com/video09/2015/09/11/3539763-535-066-0024.mp3",
                    "filesize": 2469
                }
            ],
            "shareTimes": "0",
            "duration": "316",
            "createDate": "2015-09-11 00:23:00",
            "searchPath": "55-56",
            "title": "临沂郯城：黄金大劫案告破 嫌疑人落网",
            "name": "临沂郯城：黄金大劫案告破 嫌疑人落网",
            "cpName": "齐鲁电视",
            "abstractDesc": "",
            "updateDate": "2015-09-11 00:23:00",
            "guid": "0193fa40-8693-4503-9aff-704bb4fed4c7",
            "mUrl": "http://v.ifeng.com/m/video_856341.shtml",
            "pcUrl": "http://v.ifeng.com/pc/856341.shtml",
            "itemId": "856341"
        },
        {
            "weMedia": {
                "id": "9139",
                "desc": "网罗天下国事家事天下事，穷事囧事搞笑事，事事一网打尽。",
                "name": "网罗天下",
                "headPic": "http://p3.ifengimg.com/ifengimcp/pic/20160918/c1577edef0aa54d2022f_size6_w200_h200.jpg"
            },
            "image": "http://y0.ifengimg.com/pmop/2015/04/30/962645e0-d485-41ad-9634-e4bc8074a4a0.jpg",
            "commentNo": "0",
            "playTime": "3957",
            "videoFiles": [
                {
                    "spliteNo": 0,
                    "isSplite": 0,
                    "spliteTime": "",
                    "useType": "mp4350k",
                    "mediaUrl": "http://ips.ifeng.com/3gs.ifeng.com/userfiles/video02/2015/04/30/3272415-280-068-1746.mp4",
                    "filesize": 4738
                },
                {
                    "spliteNo": 0,
                    "isSplite": 0,
                    "spliteTime": "",
                    "useType": "mp4500k",
                    "mediaUrl": "http://ips.ifeng.com/video19.ifeng.com/video09/2015/04/30/3272415-102-008-1746.mp4",
                    "filesize": 8306
                },
                {
                    "spliteNo": 0,
                    "isSplite": 0,
                    "spliteTime": "",
                    "useType": "mp3",
                    "mediaUrl": "http://ips.ifeng.com/3gs.ifeng.com/userfiles/audio02/2015/04/30/3272415-535-066-1746.mp3",
                    "filesize": 883
                }
            ],
            "shareTimes": "0",
            "duration": "113",
            "createDate": "2015-04-30 17:46:00",
            "searchPath": "55-56",
            "title": "[相关-11]",
            "name": "口罩男金店持枪上演黄金大劫案成功逃跑 警方已破获",
            "cpName": "地方台综合",
            "abstractDesc": "口罩男金店持枪上演黄金大劫案成功逃跑 警方已破获",
            "updateDate": "2016-09-04 00:36:19",
            "guid": "0140cc11-0403-4fb1-8b25-2fbdce56cc7d",
            "mUrl": "http://v.ifeng.com/m/video_3744521.shtml",
            "pcUrl": "http://v.ifeng.com/pc/3744521.shtml",
            "itemId": "3744521"
        },
        {
            "weMedia": {
                "id": "9139",
                "desc": "网罗天下国事家事天下事，穷事囧事搞笑事，事事一网打尽。",
                "name": "网罗天下",
                "headPic": "http://p3.ifengimg.com/ifengimcp/pic/20160918/c1577edef0aa54d2022f_size6_w200_h200.jpg"
            },
            "image": "http://y0.ifengimg.com/pmop/2015/04/13/fe326ffe-6e2a-4053-9b54-d0d671e77153.jpg",
            "commentNo": "0",
            "playTime": "689",
            "videoFiles": [
                {
                    "spliteNo": 0,
                    "isSplite": 0,
                    "spliteTime": "",
                    "useType": "mp4350k",
                    "mediaUrl": "http://ips.ifeng.com/3gs.ifeng.com/userfiles/video02/2015/04/13/3224365-280-068-0828.mp4",
                    "filesize": 5112
                },
                {
                    "spliteNo": 0,
                    "isSplite": 0,
                    "spliteTime": "",
                    "useType": "mp4500k",
                    "mediaUrl": "http://ips.ifeng.com/video19.ifeng.com/video09/2015/04/13/3224365-102-0821.mp4",
                    "filesize": 9859
                },
                {
                    "spliteNo": 0,
                    "isSplite": 0,
                    "spliteTime": "",
                    "useType": "mp3",
                    "mediaUrl": "http://ips.ifeng.com/3gs.ifeng.com/userfiles/audio02/2015/04/13/3224365-535-066-0828.mp3",
                    "filesize": 953
                }
            ],
            "shareTimes": "0",
            "duration": "122",
            "createDate": "2015-04-13 08:21:00",
            "searchPath": "51-53",
            "title": "[相关-12]",
            "name": "哈尔滨黄金盗窃案续：涉案金额实为三百余万",
            "cpName": "央视国际",
            "abstractDesc": "",
            "updateDate": "2015-04-13 08:21:00",
            "guid": "01daa1a8-a3d0-4ec2-8e9b-e99dbb33bc0e",
            "mUrl": "http://v.ifeng.com/m/video_1025163.shtml",
            "pcUrl": "http://v.ifeng.com/pc/1025163.shtml",
            "itemId": "1025163"
        },
        {
            "weMedia": {
                "id": "9139",
                "desc": "网罗天下国事家事天下事，穷事囧事搞笑事，事事一网打尽。",
                "name": "网罗天下",
                "headPic": "http://p3.ifengimg.com/ifengimcp/pic/20160918/c1577edef0aa54d2022f_size6_w200_h200.jpg"
            },
            "image": "http://y0.ifengimg.com/pmop/2015/04/13/f2b071f8-3b98-4616-a066-2a52d082188c.jpg",
            "commentNo": "0",
            "playTime": "688",
            "videoFiles": [
                {
                    "spliteNo": 0,
                    "isSplite": 0,
                    "spliteTime": "",
                    "useType": "mp4350k",
                    "mediaUrl": "http://ips.ifeng.com/3gs.ifeng.com/userfiles/video02/2015/04/13/3224391-280-068-0828.mp4",
                    "filesize": 5929
                },
                {
                    "spliteNo": 0,
                    "isSplite": 0,
                    "spliteTime": "",
                    "useType": "mp4500k",
                    "mediaUrl": "http://ips.ifeng.com/video19.ifeng.com/video09/2015/04/13/3224391-102-0827.mp4",
                    "filesize": 11262
                },
                {
                    "spliteNo": 0,
                    "isSplite": 0,
                    "spliteTime": "",
                    "useType": "mp3",
                    "mediaUrl": "http://ips.ifeng.com/3gs.ifeng.com/userfiles/audio02/2015/04/13/3224391-535-066-0828.mp3",
                    "filesize": 1101
                }
            ],
            "shareTimes": "0",
            "duration": "141",
            "createDate": "2015-04-13 08:27:00",
            "searchPath": "51-53",
            "title": "[相关-13]",
            "name": "警方公布黄金大劫案视频：嫌疑人伪装后行窃",
            "cpName": "央视国际",
            "abstractDesc": "",
            "updateDate": "2015-04-13 08:27:00",
            "guid": "0195a74f-73c5-4f8b-8e81-e0df1dfc0a5f",
            "mUrl": "http://v.ifeng.com/m/video_1025140.shtml",
            "pcUrl": "http://v.ifeng.com/pc/1025140.shtml",
            "itemId": "1025140"
        },
        {
            "weMedia": {
                "id": "9139",
                "desc": "网罗天下国事家事天下事，穷事囧事搞笑事，事事一网打尽。",
                "name": "网罗天下",
                "headPic": "http://p3.ifengimg.com/ifengimcp/pic/20160918/c1577edef0aa54d2022f_size6_w200_h200.jpg"
            },
            "image": "http://y0.ifengimg.com/pmop/2015/04/13/4af471c7-264a-492a-a1d9-cf5e9c222413.jpg",
            "commentNo": "1",
            "playTime": "906",
            "videoFiles": [
                {
                    "spliteNo": 0,
                    "isSplite": 0,
                    "spliteTime": "",
                    "useType": "mp4350k",
                    "mediaUrl": "http://ips.ifeng.com/3gs.ifeng.com/userfiles/video02/2015/04/13/3224393-280-068-0830.mp4",
                    "filesize": 7377
                },
                {
                    "spliteNo": 0,
                    "isSplite": 0,
                    "spliteTime": "",
                    "useType": "mp4500k",
                    "mediaUrl": "http://ips.ifeng.com/video19.ifeng.com/video09/2015/04/13/3224393-102-0830.mp4",
                    "filesize": 14987
                },
                {
                    "spliteNo": 0,
                    "isSplite": 0,
                    "spliteTime": "",
                    "useType": "mp3",
                    "mediaUrl": "http://ips.ifeng.com/3gs.ifeng.com/userfiles/audio02/2015/04/13/3224393-535-066-0830.mp3",
                    "filesize": 1375
                }
            ],
            "shareTimes": "0",
            "duration": "176",
            "createDate": "2015-04-13 08:29:00",
            "searchPath": "51-53",
            "title": "[相关-14]",
            "name": "哈尔滨黄金大劫案细节：商场保安曾遇到窃贼",
            "cpName": "央视国际",
            "abstractDesc": "",
            "updateDate": "2015-04-13 08:29:00",
            "guid": "01886cdd-e828-406b-bfb0-805a05b297b3",
            "mUrl": "http://v.ifeng.com/m/video_1025139.shtml",
            "pcUrl": "http://v.ifeng.com/pc/1025139.shtml",
            "itemId": "1025139"
        },
        {
            "weMedia": {
                "id": "9139",
                "desc": "网罗天下国事家事天下事，穷事囧事搞笑事，事事一网打尽。",
                "name": "网罗天下",
                "headPic": "http://p3.ifengimg.com/ifengimcp/pic/20160918/c1577edef0aa54d2022f_size6_w200_h200.jpg"
            },
            "image": "http://y0.ifengimg.com/pmop/2015/04/13/33fb654c-8d97-48f3-a8e2-24f41be01d34.jpg",
            "commentNo": "1",
            "playTime": "769",
            "videoFiles": [
                {
                    "spliteNo": 0,
                    "isSplite": 0,
                    "spliteTime": "",
                    "useType": "mp4350k",
                    "mediaUrl": "http://ips.ifeng.com/3gs.ifeng.com/userfiles/video02/2015/04/13/3224394-280-068-0832.mp4",
                    "filesize": 2933
                },
                {
                    "spliteNo": 0,
                    "isSplite": 0,
                    "spliteTime": "",
                    "useType": "mp4500k",
                    "mediaUrl": "http://ips.ifeng.com/video19.ifeng.com/video09/2015/04/13/3224394-102-0831.mp4",
                    "filesize": 5664
                },
                {
                    "spliteNo": 0,
                    "isSplite": 0,
                    "spliteTime": "",
                    "useType": "mp3",
                    "mediaUrl": "http://ips.ifeng.com/3gs.ifeng.com/userfiles/audio02/2015/04/13/3224394-535-066-0832.mp3",
                    "filesize": 539
                }
            ],
            "shareTimes": "0",
            "duration": "70",
            "createDate": "2015-04-13 08:31:00",
            "searchPath": "51-53",
            "title": "[相关-15]",
            "name": "揭秘哈尔滨黄金大劫案：窃贼曾为商场装修",
            "cpName": "央视国际",
            "abstractDesc": "",
            "updateDate": "2015-04-13 08:31:00",
            "guid": "016d5746-53d0-4d05-bdb7-bd106fe5952f",
            "mUrl": "http://v.ifeng.com/m/video_1025138.shtml",
            "pcUrl": "http://v.ifeng.com/pc/1025138.shtml",
            "itemId": "1025138"
        },
        {
            "weMedia": {
                "id": "9139",
                "desc": "网罗天下国事家事天下事，穷事囧事搞笑事，事事一网打尽。",
                "name": "网罗天下",
                "headPic": "http://p3.ifengimg.com/ifengimcp/pic/20160918/c1577edef0aa54d2022f_size6_w200_h200.jpg"
            },
            "image": "http://y0.ifengimg.com/pmop/2015/04/11/17d4f73a-1432-4aa2-81af-c0c23819f115.jpg",
            "commentNo": "0",
            "playTime": "435",
            "videoFiles": [
                {
                    "spliteNo": 0,
                    "isSplite": 0,
                    "spliteTime": "",
                    "useType": "mp4350k",
                    "mediaUrl": "http://ips.ifeng.com/3gs.ifeng.com/userfiles/video02/2015/04/11/3222265-280-068-1815.mp4",
                    "filesize": 3187
                },
                {
                    "spliteNo": 0,
                    "isSplite": 0,
                    "spliteTime": "",
                    "useType": "mp4500k",
                    "mediaUrl": "http://ips.ifeng.com/video19.ifeng.com/video09/2015/04/11/3222265-102-008-1815.mp4",
                    "filesize": 5261
                },
                {
                    "spliteNo": 0,
                    "isSplite": 0,
                    "spliteTime": "",
                    "useType": "mp3",
                    "mediaUrl": "http://ips.ifeng.com/3gs.ifeng.com/userfiles/audio02/2015/04/11/3222265-535-066-1815.mp3",
                    "filesize": 594
                }
            ],
            "shareTimes": "0",
            "duration": "76",
            "createDate": "2015-04-11 18:15:00",
            "searchPath": "55-56",
            "title": "[相关-16]",
            "name": "黄金大劫案告破 300万元赃物全部缴获",
            "cpName": "京视传媒",
            "abstractDesc": "",
            "updateDate": "2015-04-11 18:15:00",
            "guid": "01c2c96d-468a-4878-bfdb-0a7afb896435",
            "mUrl": "http://v.ifeng.com/m/video_1026623.shtml",
            "pcUrl": "http://v.ifeng.com/pc/1026623.shtml",
            "itemId": "1026623"
        },
        {
            "weMedia": {
                "id": "9139",
                "desc": "网罗天下国事家事天下事，穷事囧事搞笑事，事事一网打尽。",
                "name": "网罗天下",
                "headPic": "http://p3.ifengimg.com/ifengimcp/pic/20160918/c1577edef0aa54d2022f_size6_w200_h200.jpg"
            },
            "image": "http://y0.ifengimg.com/pmop/2015/04/11/e6c23483-8463-4e43-8f2f-0db5c39ff8f3.jpg",
            "commentNo": "1",
            "playTime": "532",
            "videoFiles": [
                {
                    "spliteNo": 0,
                    "isSplite": 0,
                    "spliteTime": "",
                    "useType": "mp4350k",
                    "mediaUrl": "http://ips.ifeng.com/3gs.ifeng.com/userfiles/video02/2015/04/11/3221606-280-068-0854.mp4",
                    "filesize": 3511
                },
                {
                    "spliteNo": 0,
                    "isSplite": 0,
                    "spliteTime": "",
                    "useType": "mp4500k",
                    "mediaUrl": "http://ips.ifeng.com/video19.ifeng.com/video09/2015/04/11/3221606-102-008-0854.mp4",
                    "filesize": 4327
                },
                {
                    "spliteNo": 0,
                    "isSplite": 0,
                    "spliteTime": "",
                    "useType": "mp3",
                    "mediaUrl": "http://ips.ifeng.com/3gs.ifeng.com/userfiles/audio02/2015/04/11/3221606-535-066-0854.mp3",
                    "filesize": 656
                }
            ],
            "shareTimes": "0",
            "duration": "83",
            "createDate": "2015-04-11 08:54:00",
            "searchPath": "55-56",
            "title": "[相关-17]",
            "name": "哈尔滨黄金大劫案告破26岁犯罪嫌疑人落网",
            "cpName": "东方宽频",
            "abstractDesc": "",
            "updateDate": "2015-04-11 08:54:00",
            "guid": "01629a15-8f62-45d0-a43b-87651b011d94",
            "mUrl": "http://v.ifeng.com/m/video_1027006.shtml",
            "pcUrl": "http://v.ifeng.com/pc/1027006.shtml",
            "itemId": "1027006"
        },
        {
            "weMedia": {
                "id": "9139",
                "desc": "网罗天下国事家事天下事，穷事囧事搞笑事，事事一网打尽。",
                "name": "网罗天下",
                "headPic": "http://p3.ifengimg.com/ifengimcp/pic/20160918/c1577edef0aa54d2022f_size6_w200_h200.jpg"
            },
            "image": "http://y0.ifengimg.com/pmop/2015/04/11/624bfe83-2ba8-45cd-9f15-8b9637355164.jpg",
            "commentNo": "1",
            "playTime": "1488",
            "videoFiles": [
                {
                    "spliteNo": 0,
                    "isSplite": 0,
                    "spliteTime": "",
                    "useType": "mp4350k",
                    "mediaUrl": "http://ips.ifeng.com/3gs.ifeng.com/userfiles/video02/2015/04/11/3221975-280-068-1334.mp4",
                    "filesize": 3130
                },
                {
                    "spliteNo": 0,
                    "isSplite": 0,
                    "spliteTime": "",
                    "useType": "mp4500k",
                    "mediaUrl": "http://ips.ifeng.com/video19.ifeng.com/video09/2015/04/11/3221975-102-008-1334.mp4",
                    "filesize": 5199
                },
                {
                    "spliteNo": 0,
                    "isSplite": 0,
                    "spliteTime": "",
                    "useType": "mp3",
                    "mediaUrl": "http://ips.ifeng.com/3gs.ifeng.com/userfiles/audio02/2015/04/11/3221975-535-066-1334.mp3",
                    "filesize": 586
                }
            ],
            "shareTimes": "0",
            "duration": "75",
            "createDate": "2015-04-11 13:34:00",
            "searchPath": "55-56",
            "title": "[相关-18]",
            "name": "哈尔滨黄金大劫案",
            "cpName": "京视传媒",
            "abstractDesc": "",
            "updateDate": "2015-04-11 13:34:00",
            "guid": "01e8733c-d6b1-4997-b120-e08d7bc071b0",
            "mUrl": "http://v.ifeng.com/m/video_1026734.shtml",
            "pcUrl": "http://v.ifeng.com/pc/1026734.shtml",
            "itemId": "1026734"
        },
        {
            "weMedia": {
                "id": "8724",
                "desc": "准确、及时、迅速、生动、 准时为您报导国际、经贸、社会、财经及政治新闻。",
                "name": "正点新闻",
                "headPic": "http://p2.ifengimg.com/ifengimcp/pic/20160824/1db21e83b09c6ce2745a_size27_w200_h200.jpg"
            },
            "image": "http://y0.ifengimg.com/pmop/2015/04/11/cd70f809-ceba-49fa-93ef-0e4f07377294.jpg",
            "commentNo": "0",
            "playTime": "337",
            "videoFiles": [
                {
                    "spliteNo": 0,
                    "isSplite": 0,
                    "spliteTime": "",
                    "useType": "mp4350k",
                    "mediaUrl": "http://ips.ifeng.com/3gs.ifeng.com/userfiles/video02/2015/04/11/3221360-280-068-0558.mp4",
                    "filesize": 2601
                },
                {
                    "spliteNo": 0,
                    "isSplite": 0,
                    "spliteTime": "",
                    "useType": "mp4500k",
                    "mediaUrl": "http://ips.ifeng.com/video19.ifeng.com/video09/2015/04/11/3221360-102-0558.mp4",
                    "filesize": 5233
                },
                {
                    "spliteNo": 0,
                    "isSplite": 0,
                    "spliteTime": "",
                    "useType": "mp3",
                    "mediaUrl": "http://ips.ifeng.com/3gs.ifeng.com/userfiles/audio02/2015/04/11/3221360-535-066-0558.mp3",
                    "filesize": 484
                }
            ],
            "shareTimes": "0",
            "duration": "62",
            "createDate": "2015-04-11 05:57:00",
            "searchPath": "55-56",
            "title": "[相关-19]",
            "name": "哈尔滨黄金大劫案嫌犯落网 被盗赃物已追回",
            "cpName": "凤凰卫视",
            "abstractDesc": "",
            "updateDate": "2015-04-11 05:57:00",
            "guid": "012dff9a-eec7-4496-82b0-46f444f2c8cc",
            "mUrl": "http://v.ifeng.com/m/video_1027201.shtml",
            "pcUrl": "http://v.ifeng.com/pc/1027201.shtml",
            "itemId": "1027201"
        },
        {
            "weMedia": {
                "id": "9139",
                "desc": "网罗天下国事家事天下事，穷事囧事搞笑事，事事一网打尽。",
                "name": "网罗天下",
                "headPic": "http://p3.ifengimg.com/ifengimcp/pic/20160918/c1577edef0aa54d2022f_size6_w200_h200.jpg"
            },
            "image": "http://y0.ifengimg.com/pmop/2015/04/10/4dc1a512-6195-4a5c-8028-35fa37bdd483.jpg",
            "commentNo": "0",
            "playTime": "613",
            "videoFiles": [
                {
                    "spliteNo": 0,
                    "isSplite": 0,
                    "spliteTime": "",
                    "useType": "mp4350k",
                    "mediaUrl": "http://ips.ifeng.com/3gs.ifeng.com/userfiles/video02/2015/04/10/3221191-280-068-2353.mp4",
                    "filesize": 7341
                },
                {
                    "spliteNo": 0,
                    "isSplite": 0,
                    "spliteTime": "",
                    "useType": "mp4500k",
                    "mediaUrl": "http://ips.ifeng.com/video19.ifeng.com/video09/2015/04/10/3221191-102-009-2353.mp4",
                    "filesize": 12119
                },
                {
                    "spliteNo": 0,
                    "isSplite": 0,
                    "spliteTime": "",
                    "useType": "mp3",
                    "mediaUrl": "http://ips.ifeng.com/3gs.ifeng.com/userfiles/audio02/2015/04/10/3221191-535-066-2353.mp3",
                    "filesize": 1367
                }
            ],
            "shareTimes": "0",
            "duration": "174",
            "createDate": "2015-04-10 23:53:00",
            "searchPath": "55-56",
            "title": "[相关-20]",
            "name": "哈尔滨黄金大劫案",
            "cpName": "央视国际",
            "abstractDesc": "",
            "updateDate": "2015-04-10 23:53:00",
            "guid": "01aaf331-3096-429d-b43c-1c08e8521ccd",
            "mUrl": "http://v.ifeng.com/m/video_1027289.shtml",
            "pcUrl": "http://v.ifeng.com/pc/1027289.shtml",
            "itemId": "1027289"
        },
        {
            "weMedia": {
                "id": "9139",
                "desc": "网罗天下国事家事天下事，穷事囧事搞笑事，事事一网打尽。",
                "name": "网罗天下",
                "headPic": "http://p3.ifengimg.com/ifengimcp/pic/20160918/c1577edef0aa54d2022f_size6_w200_h200.jpg"
            },
            "image": "http://y0.ifengimg.com/pmop/2015/04/10/055833aa-fad4-4a4f-8482-f16b1cf9f54b.jpg",
            "commentNo": "0",
            "playTime": "14140",
            "videoFiles": [
                {
                    "spliteNo": 0,
                    "isSplite": 0,
                    "spliteTime": "",
                    "useType": "mp4350k",
                    "mediaUrl": "http://ips.ifeng.com/3gs.ifeng.com/userfiles/video02/2015/04/10/3219161-280-068-0813.mp4",
                    "filesize": 45121
                },
                {
                    "spliteNo": 4,
                    "isSplite": 1,
                    "spliteTime": "296.96,297.08,299.80,181.76",
                    "useType": "mp4500k",
                    "mediaUrl": "http://ips.ifeng.com/video19.ifeng.com/video09/2015/04/10/3219161-102-008-0813.mp4",
                    "filesize": 74522
                },
                {
                    "spliteNo": 0,
                    "isSplite": 0,
                    "spliteTime": "",
                    "useType": "mp3",
                    "mediaUrl": "http://ips.ifeng.com/3gs.ifeng.com/userfiles/audio02/2015/04/10/3219161-535-066-0813.mp3",
                    "filesize": 8398
                }
            ],
            "shareTimes": "0",
            "duration": "1075",
            "createDate": "2015-04-10 08:13:00",
            "searchPath": "55-56",
            "title": "黄金大劫案侦破始末",
            "name": "黄金大劫案侦破始末",
            "cpName": "安徽卫视",
            "abstractDesc": "",
            "updateDate": "2015-04-10 08:13:00",
            "guid": "013cc928-bf36-469d-98f9-e49625cda9bd",
            "mUrl": "http://v.ifeng.com/m/video_1028612.shtml",
            "pcUrl": "http://v.ifeng.com/pc/1028612.shtml",
            "itemId": "1028612"
        },
        {
            "weMedia": {
                "id": "9139",
                "desc": "网罗天下国事家事天下事，穷事囧事搞笑事，事事一网打尽。",
                "name": "网罗天下",
                "headPic": "http://p3.ifengimg.com/ifengimcp/pic/20160918/c1577edef0aa54d2022f_size6_w200_h200.jpg"
            },
            "image": "http://y0.ifengimg.com/pmop/2014/09/25/6597959e-f666-4c3e-8abb-4aee95f22e21.jpg",
            "commentNo": "0",
            "playTime": "693",
            "videoFiles": [
                {
                    "spliteNo": 0,
                    "isSplite": 0,
                    "spliteTime": "",
                    "useType": "mp4350k",
                    "mediaUrl": "http://ips.ifeng.com/3gs.ifeng.com/userfiles/video02/2014/09/25/2346380-280-068-0746.mp4",
                    "filesize": 6022
                },
                {
                    "spliteNo": 0,
                    "isSplite": 0,
                    "spliteTime": "",
                    "useType": "mp4500k",
                    "mediaUrl": "http://ips.ifeng.com/video19.ifeng.com/video09/2014/09/25/2346380-102-020-0746.mp4",
                    "filesize": 10000
                },
                {
                    "spliteNo": 0,
                    "isSplite": 0,
                    "spliteTime": "",
                    "useType": "mp3",
                    "mediaUrl": "http://ips.ifeng.com/3gs.ifeng.com/userfiles/audio02/2014/09/25/2346380-535-066-0746.mp3",
                    "filesize": 1117
                }
            ],
            "shareTimes": "0",
            "duration": "143",
            "createDate": "2014-09-25 07:46:00",
            "searchPath": "55-56",
            "title": "河南：破获百万黄金大劫案 嫌疑人网络结识",
            "name": "河南：破获百万黄金大劫案 嫌疑人网络结识",
            "cpName": "河北广电",
            "abstractDesc": "",
            "updateDate": "2014-09-25 07:46:00",
            "guid": "016c9196-af89-4aa2-93de-ff167dceb6e9",
            "mUrl": "http://v.ifeng.com/m/video_1480009.shtml",
            "pcUrl": "http://v.ifeng.com/pc/1480009.shtml",
            "itemId": "1480009"
        },
        {
            "weMedia": {
                "id": "9139",
                "desc": "网罗天下国事家事天下事，穷事囧事搞笑事，事事一网打尽。",
                "name": "网罗天下",
                "headPic": "http://p3.ifengimg.com/ifengimcp/pic/20160918/c1577edef0aa54d2022f_size6_w200_h200.jpg"
            },
            "image": "http://y0.ifengimg.com/pmop/2014/09/24/326f0f90-2196-4917-a1c7-39693f15aeb0.jpg",
            "commentNo": "0",
            "playTime": "214",
            "videoFiles": [
                {
                    "spliteNo": 0,
                    "isSplite": 0,
                    "spliteTime": "",
                    "useType": "mp4350k",
                    "mediaUrl": "http://ips.ifeng.com/3gs.ifeng.com/userfiles/video02/2014/09/24/2338348-280-068-0747.mp4",
                    "filesize": 4710
                },
                {
                    "spliteNo": 0,
                    "isSplite": 0,
                    "spliteTime": "",
                    "useType": "mp4500k",
                    "mediaUrl": "http://ips.ifeng.com/video19.ifeng.com/video09/2014/09/24/2338348-102-008-0747.mp4",
                    "filesize": 7832
                },
                {
                    "spliteNo": 0,
                    "isSplite": 0,
                    "spliteTime": "",
                    "useType": "mp3",
                    "mediaUrl": "http://ips.ifeng.com/3gs.ifeng.com/userfiles/audio02/2014/09/24/2338348-535-066-0747.mp3",
                    "filesize": 875
                }
            ],
            "shareTimes": "0",
            "duration": "112",
            "createDate": "2014-09-24 07:47:00",
            "searchPath": "55-56",
            "title": "[相关-21]",
            "name": "河南破获百万黄金大劫案 嫌疑人网络结识",
            "cpName": "山东卫视",
            "abstractDesc": "",
            "updateDate": "2014-09-24 07:47:00",
            "guid": "01f98188-209d-4477-888f-20952c7f186d",
            "mUrl": "http://v.ifeng.com/m/video_1483470.shtml",
            "pcUrl": "http://v.ifeng.com/pc/1483470.shtml",
            "itemId": "1483470"
        },
        {
            "weMedia": {
                "id": "9139",
                "desc": "网罗天下国事家事天下事，穷事囧事搞笑事，事事一网打尽。",
                "name": "网罗天下",
                "headPic": "http://p3.ifengimg.com/ifengimcp/pic/20160918/c1577edef0aa54d2022f_size6_w200_h200.jpg"
            },
            "image": "http://y0.ifengimg.com/pmop/2014/06/23/42896b9b-5b12-4f4f-a155-f00bc18cecbf.jpg",
            "commentNo": "0",
            "playTime": "533",
            "videoFiles": [
                {
                    "spliteNo": 0,
                    "isSplite": 0,
                    "spliteTime": "",
                    "useType": "mp4350k",
                    "mediaUrl": "http://ips.ifeng.com/3gs.ifeng.com/userfiles/video02/2014/06/23/2025283-280-068-0004.mp4",
                    "filesize": 883
                },
                {
                    "spliteNo": 0,
                    "isSplite": 0,
                    "spliteTime": "",
                    "useType": "mp4500k",
                    "mediaUrl": "http://ips.ifeng.com/video19.ifeng.com/video09/2014/06/23/2025283-102-009-0004.mp4",
                    "filesize": 1486
                },
                {
                    "spliteNo": 0,
                    "isSplite": 0,
                    "spliteTime": "",
                    "useType": "mp3",
                    "mediaUrl": "http://ips.ifeng.com/3gs.ifeng.com/userfiles/audio02/2014/06/23/2025283-535-066-0004.mp3",
                    "filesize": 164
                }
            ],
            "shareTimes": "0",
            "duration": "21",
            "createDate": "2014-06-22 00:04:00",
            "searchPath": "55-56",
            "title": "[相关-22]",
            "name": "60秒黄金大劫案23小时告破",
            "cpName": "央视国际",
            "abstractDesc": "",
            "updateDate": "2014-06-22 00:04:00",
            "guid": "01c2aaa6-08fd-4d11-a615-ab17b0bf7b7e",
            "mUrl": "http://v.ifeng.com/m/video_1774007.shtml",
            "pcUrl": "http://v.ifeng.com/pc/1774007.shtml",
            "itemId": "1774007"
        },
        {
            "weMedia": {
                "id": "9139",
                "desc": "网罗天下国事家事天下事，穷事囧事搞笑事，事事一网打尽。",
                "name": "网罗天下",
                "headPic": "http://p3.ifengimg.com/ifengimcp/pic/20160918/c1577edef0aa54d2022f_size6_w200_h200.jpg"
            },
            "image": "http://y0.ifengimg.com/pmop/2014/06/23/af521396-8519-4072-8991-825cc7a0aa9a.jpg",
            "commentNo": "0",
            "playTime": "178",
            "videoFiles": [
                {
                    "spliteNo": 0,
                    "isSplite": 0,
                    "spliteTime": "",
                    "useType": "mp4350k",
                    "mediaUrl": "http://ips.ifeng.com/3gs.ifeng.com/userfiles/video02/2014/06/23/2025280-280-068-0004.mp4",
                    "filesize": 5041
                },
                {
                    "spliteNo": 0,
                    "isSplite": 0,
                    "spliteTime": "",
                    "useType": "mp4500k",
                    "mediaUrl": "http://ips.ifeng.com/video19.ifeng.com/video09/2014/06/23/2025280-102-009-0004.mp4",
                    "filesize": 8346
                },
                {
                    "spliteNo": 0,
                    "isSplite": 0,
                    "spliteTime": "",
                    "useType": "mp3",
                    "mediaUrl": "http://ips.ifeng.com/3gs.ifeng.com/userfiles/audio02/2014/06/23/2025280-535-066-0004.mp3",
                    "filesize": 937
                }
            ],
            "shareTimes": "0",
            "duration": "120",
            "createDate": "2014-06-22 00:04:00",
            "searchPath": "55-56",
            "title": "[相关-23]",
            "name": "贵州贵阳60秒黄金大劫案",
            "cpName": "央视国际",
            "abstractDesc": "",
            "updateDate": "2014-06-22 00:04:00",
            "guid": "0178a66d-73a7-402a-a430-42dd18c441a6",
            "mUrl": "http://v.ifeng.com/m/video_1774009.shtml",
            "pcUrl": "http://v.ifeng.com/pc/1774009.shtml",
            "itemId": "1774009"
        },
        {
            "weMedia": {
                "id": "9139",
                "desc": "网罗天下国事家事天下事，穷事囧事搞笑事，事事一网打尽。",
                "name": "网罗天下",
                "headPic": "http://p3.ifengimg.com/ifengimcp/pic/20160918/c1577edef0aa54d2022f_size6_w200_h200.jpg"
            },
            "image": "http://y0.ifengimg.com/pmop/2014/01/08/46354db5-0238-40cb-9b3f-b9fd2ca9fcb0.jpg",
            "commentNo": "0",
            "playTime": "64639",
            "videoFiles": [
                {
                    "spliteNo": 0,
                    "isSplite": 0,
                    "spliteTime": "",
                    "useType": "mp4350k",
                    "mediaUrl": "http://ips.ifeng.com/3gs.ifeng.com/userfiles/video01/2014/01/08/1641508-280-068-0837.mp4",
                    "filesize": 44312
                },
                {
                    "spliteNo": 0,
                    "isSplite": 0,
                    "spliteTime": "",
                    "useType": "mp4500k",
                    "mediaUrl": "http://ips.ifeng.com/video19.ifeng.com/video07/2014/01/08/1641508-102-008-0837.mp4",
                    "filesize": 82459
                },
                {
                    "spliteNo": 0,
                    "isSplite": 0,
                    "spliteTime": "",
                    "useType": "mp3",
                    "mediaUrl": "http://ips.ifeng.com/3gs.ifeng.com/userfiles/audio01/2014/01/08/1641508-535-066-0837.mp3",
                    "filesize": 9290
                }
            ],
            "shareTimes": "0",
            "duration": "1189",
            "createDate": "2014-01-08 08:37:00",
            "searchPath": "55-56",
            "title": "[相关-24]",
            "name": "小镇上的黄金大劫案",
            "cpName": "安徽卫视",
            "abstractDesc": "",
            "updateDate": "2014-01-08 08:37:00",
            "guid": "01c06860-fede-4acf-a3c2-0febd747f3a4",
            "mUrl": "http://v.ifeng.com/m/video_2239966.shtml",
            "pcUrl": "http://v.ifeng.com/pc/2239966.shtml",
            "itemId": "2239966"
        },
        {
            "weMedia": {
                "id": "9139",
                "desc": "网罗天下国事家事天下事，穷事囧事搞笑事，事事一网打尽。",
                "name": "网罗天下",
                "headPic": "http://p3.ifengimg.com/ifengimcp/pic/20160918/c1577edef0aa54d2022f_size6_w200_h200.jpg"
            },
            "image": "http://y0.ifengimg.com/image/2013/11/18/00489cbc-8cb6-48d8-b738-c1870789dd2a.jpg",
            "commentNo": "0",
            "playTime": "215",
            "videoFiles": [
                {
                    "spliteNo": 0,
                    "isSplite": 0,
                    "spliteTime": "",
                    "useType": "mp4350k",
                    "mediaUrl": "http://ips.ifeng.com/3gs.ifeng.com/userfiles/video01/2013/11/18/294158-280-068-1304.mp4",
                    "filesize": 4891
                },
                {
                    "spliteNo": 0,
                    "isSplite": 0,
                    "spliteTime": "",
                    "useType": "mp4500k",
                    "mediaUrl": "http://ips.ifeng.com/video19.ifeng.com/video07/2013/11/18/294158-102-008-1304.mp4",
                    "filesize": 9097
                },
                {
                    "spliteNo": 0,
                    "isSplite": 0,
                    "spliteTime": "",
                    "useType": "mp3",
                    "mediaUrl": "http://ips.ifeng.com/3gs.ifeng.com/userfiles/audio01/2013/11/18/294158-535-066-1304.mp3",
                    "filesize": 501
                }
            ],
            "shareTimes": "0",
            "duration": "128",
            "createDate": "2013-11-18 13:04:00",
            "searchPath": "55-56",
            "title": "[相关-25]",
            "name": "商场上演真实版黄金大劫案",
            "cpName": "京视传媒",
            "abstractDesc": "",
            "updateDate": "2013-11-18 13:04:00",
            "guid": "0155ab9b-8753-45e0-837a-db15701f8fc4",
            "mUrl": "http://v.ifeng.com/m/video_2391751.shtml",
            "pcUrl": "http://v.ifeng.com/pc/2391751.shtml",
            "itemId": "2391751"
        }
    ]
}